shimoku_tangram/__init__.py
shimoku_tangram/formatting/dates.py
shimoku_tangram/orchestration/step_functions.py
shimoku_tangram/reporting/logging.py
shimoku_tangram/reporting/sentry.py
shimoku_tangram/secrets/secrets_manager.py
shimoku_tangram/secrets/ssm.py
shimoku_tangram/storage/meta_s3.py
shimoku_tangram/storage/s3.py
shimoku_tangram-0.1.0.dist-info/METADATA
shimoku_tangram-0.1.0.dist-info/WHEEL
shimoku_tangram-0.1.0.dist-info/RECORD
