Metadata-Version: 2.3
Name: shimoku-tangram
Version: 0.1.0
Summary: 
Author: edgar
Author-email: edgar.sarria@shimoku.com
Requires-Python: >=3.10,<4.0
Classifier: Programming Language :: Python :: 3
Classifier: Programming Language :: Python :: 3.10
Classifier: Programming Language :: Python :: 3.11
Classifier: Programming Language :: Python :: 3.12
Classifier: Programming Language :: Python :: 3.13
Requires-Dist: aws-xray-sdk (==2.14.0)
Requires-Dist: boto3 (>=1.34.121,<2.0.0)
Requires-Dist: pandas (>=2.2.2)
Requires-Dist: sentry-sdk (>=2.5.1,<3.0.0)
